log4mongo/__init__.py
log4mongo/_version.py
log4mongo/handlers.py
log4mongo-1.8.1.dist-info/LICENSE
log4mongo-1.8.1.dist-info/METADATA
log4mongo-1.8.1.dist-info/WHEEL
log4mongo-1.8.1.dist-info/top_level.txt
log4mongo-1.8.1.dist-info/RECORD
